<?xml version="1.0" encoding="UTF-8"?><record_update table="sys_atf_step">
    <sys_atf_step action="DELETE">
        <active>true</active>
        <copied_from display_value="Log">30553439972e35103a90b5a6f053af9f</copied_from>
        <description>Log: When needed に過去の日付は指定不可　</description>
        <display_name>Log</display_name>
        <inputs/>
        <mugshots_cache_json/>
        <notes/>
        <order>4</order>
        <step_config display_value="Log">58ab71985f30220012b44adb7f46661e</step_config>
        <sys_class_name>sys_atf_step</sys_class_name>
        <sys_created_by>admin</sys_created_by>
        <sys_created_on>2023-11-17 05:52:28</sys_created_on>
        <sys_id>d5bd74b1976e35103a90b5a6f053afe2</sys_id>
        <sys_mod_count>3</sys_mod_count>
        <sys_name>Log</sys_name>
        <sys_package display_value="NeedIt" source="x_58872_needit">6ead8e780f603200cd674f8ce1050ed1</sys_package>
        <sys_policy/>
        <sys_scope display_value="NeedIt">6ead8e780f603200cd674f8ce1050ed1</sys_scope>
        <sys_update_name>sys_atf_step_d5bd74b1976e35103a90b5a6f053afe2</sys_update_name>
        <sys_updated_by>admin</sys_updated_by>
        <sys_updated_on>2023-11-17 06:08:05</sys_updated_on>
        <table/>
        <test display_value="When needed - Future past">01bd7c31976e35103a90b5a6f053af0c</test>
        <timeout/>
        <warning_message/>
    </sys_atf_step>
    <sys_variable_value action="DELETE" query="document_key=d5bd74b1976e35103a90b5a6f053afe2"/>
    <sys_variable_value action="DELETE">
        <document>sys_atf_step</document>
        <document_key>d5bd74b1976e35103a90b5a6f053afe2</document_key>
        <order>100</order>
        <sys_class_name>sys_variable_value</sys_class_name>
        <sys_created_by>admin</sys_created_by>
        <sys_created_on>2023-11-17 05:52:28</sys_created_on>
        <sys_id>99bd74b1976e35103a90b5a6f053afe3</sys_id>
        <sys_mod_count>3</sys_mod_count>
        <sys_updated_by>admin</sys_updated_by>
        <sys_updated_on>2023-11-17 06:08:05</sys_updated_on>
        <value>When needed に過去の日付は指定不可　</value>
        <variable display_value="Log">523c79985f30220012b44adb7f46663a</variable>
    </sys_variable_value>
    <sys_element_mapping action="DELETE" query="table=var__m_atf_input_variable_58ab71985f30220012b44adb7f46661e^id=d5bd74b1976e35103a90b5a6f053afe2"/>
    <sys_update_version action="INSERT_OR_UPDATE">
        <action>DELETE</action>
        <application display_value="NeedIt">6ead8e780f603200cd674f8ce1050ed1</application>
        <file_path/>
        <instance_id>54ee0f98db47b38452dd2f17d4961915</instance_id>
        <instance_name>dev89920</instance_name>
        <name>sys_atf_step_d5bd74b1976e35103a90b5a6f053afe2</name>
        <payload><![CDATA[<?xml version="1.0" encoding="UTF-8"?><record_update table="sys_atf_step"><sys_atf_step action="INSERT_OR_UPDATE"><active>true</active><copied_from display_value="Log">30553439972e35103a90b5a6f053af9f</copied_from><description>Log: When needed に過去の日付は指定不可　</description><display_name>Log</display_name><inputs/><mugshots_cache_json/><notes/><order>4</order><step_config display_value="Log">58ab71985f30220012b44adb7f46661e</step_config><sys_class_name>sys_atf_step</sys_class_name><sys_created_by>admin</sys_created_by><sys_created_on>2023-11-17 05:52:28</sys_created_on><sys_id>d5bd74b1976e35103a90b5a6f053afe2</sys_id><sys_mod_count>3</sys_mod_count><sys_name>Log</sys_name><sys_package display_value="NeedIt" source="x_58872_needit">6ead8e780f603200cd674f8ce1050ed1</sys_package><sys_policy/><sys_scope display_value="NeedIt">6ead8e780f603200cd674f8ce1050ed1</sys_scope><sys_update_name>sys_atf_step_d5bd74b1976e35103a90b5a6f053afe2</sys_update_name><sys_updated_by>admin</sys_updated_by><sys_updated_on>2023-11-17 06:08:05</sys_updated_on><table/><test display_value="When needed - Future past">01bd7c31976e35103a90b5a6f053af0c</test><timeout/><warning_message/></sys_atf_step><sys_variable_value action="delete_multiple" query="document_key=d5bd74b1976e35103a90b5a6f053afe2"/><sys_variable_value action="INSERT_OR_UPDATE"><document>sys_atf_step</document><document_key>d5bd74b1976e35103a90b5a6f053afe2</document_key><order>100</order><sys_class_name>sys_variable_value</sys_class_name><sys_created_by>admin</sys_created_by><sys_created_on>2023-11-17 05:52:28</sys_created_on><sys_id>99bd74b1976e35103a90b5a6f053afe3</sys_id><sys_mod_count>3</sys_mod_count><sys_updated_by>admin</sys_updated_by><sys_updated_on>2023-11-17 06:08:05</sys_updated_on><value>When needed に過去の日付は指定不可　</value><variable display_value="Log">523c79985f30220012b44adb7f46663a</variable></sys_variable_value><sys_element_mapping action="delete_multiple" query="table=var__m_atf_input_variable_58ab71985f30220012b44adb7f46661e^id=d5bd74b1976e35103a90b5a6f053afe2"/></record_update>]]></payload>
        <payload_hash>-601768382</payload_hash>
        <record_name>Log</record_name>
        <reverted_from/>
        <source>f953a4f997c631103a90b5a6f053afeb</source>
        <source_table>sys_update_set</source_table>
        <state>previous</state>
        <sys_created_by>admin</sys_created_by>
        <sys_created_on>2023-11-17 06:08:05</sys_created_on>
        <sys_id>064149b5976e35103a90b5a6f053afdc</sys_id>
        <sys_mod_count>0</sys_mod_count>
        <sys_recorded_at>18bdbe4c83d0000001</sys_recorded_at>
        <sys_updated_by>admin</sys_updated_by>
        <sys_updated_on>2023-11-17 06:08:05</sys_updated_on>
        <type>Test Step</type>
        <update_guid>ca4149b5eb6e35103c262a588315b7db</update_guid>
        <update_guid_history>ca4149b5eb6e35103c262a588315b7db:-601768382,aca00135b16e3510c5db5e21c6807957:1751075669,55bd74b16c6e351065bff282b49b2eeb:854875811,59bd74b1c26e351022ab0392ff21c9e5:-793110989</update_guid_history>
    </sys_update_version>
    <sys_metadata_delete action="INSERT_OR_UPDATE">
        <sys_audit_delete/>
        <sys_class_name>sys_metadata_delete</sys_class_name>
        <sys_created_by>admin</sys_created_by>
        <sys_created_on>2023-11-17 06:31:04</sys_created_on>
        <sys_db_object display_value="" name="sys_atf_step">sys_atf_step</sys_db_object>
        <sys_id>0f7ea6aa181a4d3c9d1ebb6abc684d10</sys_id>
        <sys_metadata>d5bd74b1976e35103a90b5a6f053afe2</sys_metadata>
        <sys_mod_count>0</sys_mod_count>
        <sys_name>Log</sys_name>
        <sys_package display_value="NeedIt" source="x_58872_needit">6ead8e780f603200cd674f8ce1050ed1</sys_package>
        <sys_parent/>
        <sys_policy/>
        <sys_scope display_value="NeedIt">6ead8e780f603200cd674f8ce1050ed1</sys_scope>
        <sys_scope_delete display_value="">94872a8897db403e8ee69a431de2fca4</sys_scope_delete>
        <sys_update_name>sys_atf_step_d5bd74b1976e35103a90b5a6f053afe2</sys_update_name>
        <sys_update_version display_value="sys_atf_step_d5bd74b1976e35103a90b5a6f053afe2">064149b5976e35103a90b5a6f053afdc</sys_update_version>
        <sys_updated_by>admin</sys_updated_by>
        <sys_updated_on>2023-11-17 06:31:04</sys_updated_on>
    </sys_metadata_delete>
</record_update>
